[{"name":"Radioactive Heat","colors":["#F7941E","#72C6EF","#00A651"],"slug":"radioactive-heat","hues":["oranges","cyans","cyans"]},{"name":"The Sky And The Sea","colors":["#F7941E","#004E8F"],"slug":"the-sky-and-the-sea","hues":["oranges","cyans"]},{"name":"Summer Breeze","colors":["#fbed96","#abecd6"],"slug":"summer-breeze","hues":["oranges","cyans"]},{"name":"Ver","colors":["#FFE000","#799F0C"],"slug":"ver","hues":["oranges","yellows"]},{"name":"Combi","colors":["#00416A","#799F0C","#FFE000"],"slug":"combi","hues":["cyans","yellows","oranges"]},{"name":"Anwar","colors":["#334d50","#cbcaa5"],"slug":"anwar","hues":["cyans","oranges"]},{"name":"Mango","colors":["#ffe259","#ffa751"],"slug":"mango","hues":["oranges","oranges"]},{"name":"Rea","colors":["#FFE000","#799F0C"],"slug":"rea","hues":["oranges","yellows"]},{"name":"Blooker20","colors":["#e65c00","#F9D423"],"slug":"blooker20","hues":["reds","oranges"]},{"name":"Harmonic Energy","colors":["#16A085","#F4D03F"],"slug":"harmonic-energy","hues":["cyans","oranges"]},{"name":"Sunny Days","colors":["#EDE574","#E1F5C4"],"slug":"sunny-days","hues":["oranges","whites"]},{"name":"Lemon Twist","colors":["#3CA55C","#B5AC49"],"slug":"lemon-twist","hues":["greens","oranges"]},{"name":"Monte Carlo","colors":["#CC95C0","#DBD4B4","#7AA1D2"],"slug":"monte-carlo","hues":["magentas","oranges","blues"]},{"name":"Mango Pulp","colors":["#F09819","#EDDE5D"],"slug":"mango-pulp","hues":["oranges","oranges"]},{"name":"Sunrise","colors":["#FF512F","#F09819"],"slug":"sunrise","hues":["reds","oranges"]},{"name":"Juicy Orange","colors":["#FF8008","#FFC837"],"slug":"juicy-orange","hues":["oranges","oranges"]},{"name":"Opa","colors":["#3D7EAA","#FFE47A"],"slug":"opa","hues":["cyans","oranges"]},{"name":"Blurry Beach","colors":["#d53369","#cbad6d"],"slug":"blurry-beach","hues":["Reds","oranges"]},{"name":"Vasily","colors":["#e9d362","#333333"],"slug":"vasily","hues":["oranges","grays"]},{"name":"Kyoto","colors":["#c21500","#ffc500"],"slug":"kyoto","hues":["reds","oranges"]},{"name":"Autumn","colors":["#DAD299","#B0DAB9"],"slug":"autumn","hues":["oranges","greens"]},{"name":"Earthly","colors":["#649173","#DBD5A4"],"slug":"earthly","hues":["grays","oranges"]},{"name":"Dance To Forget","colors":["#FF4E50","#F9D423"],"slug":"dance-to-forget","hues":["Reds","oranges"]},{"name":"Starfall","colors":["#F0C27B","#4B1248"],"slug":"starfall","hues":["oranges","blacks"]},{"name":"Shore","colors":["#70e1f5","#ffd194"],"slug":"shore","hues":["cyans","oranges"]},{"name":"SoundCloud","colors":["#fe8c00","#f83600"],"slug":"soundcloud","hues":["oranges","reds"]},{"name":"Crazy Orange I","colors":["#D38312","#A83279"],"slug":"crazy-orange-i","hues":["oranges","magentas"]},{"name":"Pastel Orange at the Sun","colors":["#ffb347","#ffcc33"],"slug":"pastel-orange-at-the-sun","hues":["oranges","oranges"]},{"name":"Atlas","colors":["#FEAC5E","#C779D0","#4BC0C8"],"slug":"atlas","hues":["oranges","magentas","cyans"]},{"name":"Instagram","colors":["#833ab4","#fd1d1d","#fcb045"],"slug":"instagram","hues":["magentas","reds","oranges"]},{"name":"Koko Caramel","colors":["#D1913C","#FFD194"],"slug":"koko-caramel","hues":["oranges","oranges"]},{"name":"Ukraine","colors":["#004FF9","#FFF94C"],"slug":"ukraine","hues":["blues","oranges"]},{"name":"Dark Knight","colors":["#BA8B02","#181818"],"slug":"dark-knight","hues":["oranges","blacks"]},{"name":"Master Card","colors":["#f46b45","#eea849"],"slug":"master-card","hues":["reds","oranges"]},{"name":"Light Orange","colors":["#FFB75E","#ED8F03"],"slug":"light-orange","hues":["oranges","oranges"]},{"name":"Back to the Future","colors":["#C02425","#F0CB35"],"slug":"back-to-the-future","hues":["Reds","oranges"]},{"name":"Pale Wood","colors":["#eacda3","#d6ae7b"],"slug":"pale-wood","hues":["oranges","oranges"]},{"name":"Minnesota Vikings","colors":["#5614B0","#DBD65C"],"slug":"minnesota-vikings","hues":["blues","oranges"]},{"name":"Miami Dolphins","colors":["#4DA0B0","#D39D38"],"slug":"miami-dolphins","hues":["cyans","oranges"]},{"name":"Tranquil","colors":["#EECDA3","#EF629F"],"slug":"tranquil","hues":["oranges","Reds"]},{"name":"Sweet Morning","colors":["#FF5F6D","#FFC371"],"slug":"sweet-morning","hues":["Reds","oranges"]},{"name":"Sherbert","colors":["#f79d00","#64f38c"],"slug":"sherbert","hues":["oranges","greens"]},{"name":"Sun on the Horizon","colors":["#fceabb","#f8b500"],"slug":"sun-on-the-horizon","hues":["whites","oranges"]},{"name":"Jupiter","colors":["#ffd89b","#19547b"],"slug":"jupiter","hues":["oranges","cyans"]},{"name":"Learning and Leading","colors":["#F7971E","#FFD200"],"slug":"learning-and-leading","hues":["oranges","oranges"]},{"name":"Sunkist","colors":["#F2994A","#F2C94C"],"slug":"sunkist","hues":["reds","oranges"]},{"name":"Summer","colors":["#22c1c3","#fdbb2d"],"slug":"summer","hues":["cyans","oranges"]},{"name":"King Yna","colors":["#1a2a6c","#b21f1f","#fdbb2d"],"slug":"king-yna","hues":["blues","reds","oranges"]},{"name":"Lithium","colors":["#6D6027","#D3CBB8"],"slug":"lithium","hues":["oranges","oranges"]},{"name":"Orange Fun","colors":["#fc4a1a","#f7b733"],"slug":"orange-fun","hues":["reds","oranges"]},{"name":"Sulphur","colors":["#CAC531","#F3F9A7"],"slug":"sulphur","hues":["oranges","yellows"]},{"name":"Selenium","colors":["#3C3B3F","#605C3C"],"slug":"selenium","hues":["grays","oranges"]},{"name":"Sand to Blue","colors":["#3E5151","#DECBA4"],"slug":"sand-to-blue","hues":["grays","oranges"]},{"name":"Wedding Day Blues","colors":["#40E0D0","#FF8C00","#FF0080"],"slug":"wedding-day-blues","hues":["cyans","oranges","Reds"]},{"name":"Citrus Peel","colors":["#FDC830","#F37335"],"slug":"citrus-peel","hues":["oranges","reds"]},{"name":"Rastafari","colors":["#1E9600","#FFF200","#FF0000"],"slug":"rastafari","hues":["greens","oranges","reds"]},{"name":"Kyoo Tah","colors":["#544a7d","#ffd452"],"slug":"kyoo-tah","hues":["blues","oranges"]},{"name":"Flare","colors":["#f12711","#f5af19"],"slug":"flare","hues":["reds","oranges"]},{"name":"MegaTron","colors":["#C6FFDD","#FBD786","#f7797d"],"slug":"megatron","hues":["whites","oranges","Reds"]},{"name":"Zenta","colors":["#2A2D3E","#FECB6E"],"slug":"zenta","hues":["blues","oranges"]},{"name":"Newspaper","colors":["#8a2be2","#ffa500","#f8f8ff"],"slug":"newspaper","hues":["magentas","oranges","whites"]},{"name":"Lemon Lime","colors":["#7ec6bc","#ebe717"],"slug":"lemon-lime","hues":["cyans","oranges"]},{"name":"Beleko","colors":["#ff1e56","#f9c942","#1e90ff"],"slug":"beleko","hues":["Reds","oranges","blues"]},{"name":"Unicorn Rainbow","colors":["#f7f0ac","#acf7f0","#f0acf7"],"slug":"unicorn-rainbow","hues":["oranges","cyans","magentas"]},{"name":"Flame","colors":["#ff0000","#fdcf58"],"slug":"flame","hues":["reds","oranges"]},{"name":"Coffee Gold","colors":["#554023","#c99846"],"slug":"coffee-gold","hues":["oranges","oranges"]},{"name":"After the Rain","colors":["#ff75c3","#ffa647","#ffe83f","#9fff5b","#70e2ff","#cd93ff"],"slug":"after-the-rain","hues":["magentas","oranges","oranges","greens","cyans","magentas"]}]